.gitignore
.travis.yml
CHANGES.md
LICENSE
MANIFEST.in
README.md
requirements.txt
setup.py
datasets/README.ipynb
datasets/__init__.py
datasets/demo1.py
datasets/demo2.py
nbs/dim - PCA.ipynb
nbs/example - MultiBinaryToMultiClass.ipynb
nbs/example - Probability Recalibration.ipynb
nbs/out - Outlier.ipynb
nbs/pdf - Density.ipynb
nbs/sbmi - Logistic Lasso.ipynb
nbs/sbmi - Logistic Ridge.ipynb
nbs/simi - Bayesian.ipynb
nbs/simi - ElasticNet.ipynb
nbs/simi - Lasso.ipynb
nbs/simi - Ridge.ipynb
nbs/simi - Robust.ipynb
potpourri/__init__.py
potpourri/sbmi1.py
potpourri/sbmi25.py
potpourri/sbmi56.py
potpourri/sbmi57.py
potpourri/sbmi58.py
potpourri/sbmi59.py
potpourri/sbmi60.py
potpourri/sbmi93.py
potpourri/sbmi94.py
potpourri/sbmi95.py
potpourri/sbmi96.py
potpourri/sbmi97.py
potpourri/simi1.py
potpourri/simi10.py
potpourri/simi11.py
potpourri/simi12.py
potpourri/simi13.py
potpourri/simi14.py
potpourri/simi15.py
potpourri/simi16.py
potpourri/simi2.py
potpourri/simi3.py
potpourri/simi4.py
potpourri/simi5.py
potpourri/simi6.py
potpourri/simi7.py
potpourri/simi8.py
potpourri/simi9.py
potpourri.egg-info/PKG-INFO
potpourri.egg-info/SOURCES.txt
potpourri.egg-info/dependency_links.txt
potpourri.egg-info/not-zip-safe
potpourri.egg-info/requires.txt
potpourri.egg-info/top_level.txt
seasalt/__init__.py
seasalt/calibrate_on_leaves.py
seasalt/cluster_transformer.py
seasalt/create_feature_names.py
seasalt/multi_binary_to_multi_class.py
seasalt/multi_output_classifier2.py
seasalt/proba_transformer.py
seasalt/refit_model.py
seasalt/sb.py
seasalt/select_the_best.py
seasalt/si.py
seasalt/store_models.py
seasalt/transformer_custom_settings.py
seasalt/transformer_default_settings.py
verto/__init__.py
verto/clu1.py
verto/dim1.py
verto/dim2.py
verto/dim3.py
verto/dim4.py
verto/dim5.py
verto/dim6.py
verto/nb1.py
verto/out1.py
verto/pdf1.py
verto/raw1.py
verto/rnd1.py
verto/scl1.py