Metadata-Version: 2.1
Name: potpourri
Version: 0.14.0
Summary: model zoo of different preconfigured algorithms
Home-page: http://github.com/kmedian/potpourri
Author: Ulf Hamster
Author-email: 554c46@gmail.com
License: MIT
Platform: UNKNOWN
Requires-Python: >=3.6
